{
  "posted_ids": [
    "006",
    "003",
    "011",
    "010",
    "009",
    "007",
    "032",
    "001",
    "016",
    "033",
    "022",
    "027",
    "036",
    "044",
    "042",
    "020",
    "019"
  ],
  "last_post_time": "2026-07-12T07:57:31.830718",
  "last_post_id": "2076214357256536363",
  "next_wait_minutes": 529,
  "recent_pillars": [
    "Download",
    "Calendar",
    "Reports",
    "Jobs",
    "Offline",
    "Calculators"
  ],
  "recent_cards": [
    "ad-7.png",
    "ad-6.png",
    "ad-4.png",
    "ad-2.png",
    "ad-10.png",
    "ad-9.png"
  ]
}