{
  "posted_ids": [
    "001",
    "006",
    "004",
    "010",
    "003",
    "015",
    "009",
    "007",
    "014",
    "011",
    "019",
    "016",
    "020",
    "017",
    "013",
    "029",
    "022",
    "027",
    "028",
    "036",
    "030",
    "035",
    "039",
    "023",
    "042",
    "045",
    "041",
    "033",
    "044",
    "040",
    "048",
    "043",
    "046",
    "032",
    "055",
    "053",
    "059",
    "002",
    "058",
    "066",
    "065",
    "067",
    "049",
    "056",
    "068",
    "054",
    "061",
    "069",
    "062",
    "084",
    "081",
    "080",
    "077",
    "026",
    "072",
    "071",
    "075",
    "074",
    "078",
    "092",
    "093",
    "085",
    "097"
  ],
  "last_post_time": "2026-07-20T22:05:30.628713",
  "last_post_id": "122131268457194814",
  "recent_pillars": [
    "Weather",
    "Quick Win",
    "Download",
    "Pain",
    "Offline",
    "Calculators"
  ],
  "recent_cards": [
    "ad-4.png",
    "ad-8.png",
    "ad-2.png",
    "ad-3.png",
    "ad-5.png",
    "ad-7.png"
  ]
}